soundviewer/__init__.py
soundviewer/image2sound.py
soundviewer/sound2image.py
soundviewer-1.0.2.dist-info/LICENSE
soundviewer-1.0.2.dist-info/WHEEL
soundviewer-1.0.2.dist-info/METADATA
soundviewer-1.0.2.dist-info/RECORD
