Metadata-Version: 2.1
Name: soundviewer
Version: 1.0.2
Summary: Python package for sound visualization
Author-email: emingenc <emingench@yandex.com>
Classifier: License :: OSI Approved :: GNU General Public License v3 or later (GPLv3+)
Requires-Dist: librosa>=0.9.0
Requires-Dist: matplotlib>=3.5.1
Requires-Dist: audio-metadata>=0.11.1
Requires-Dist: opencv-python>=4.5.5.62
Project-URL: Home, https://github.com/emingenc/soundviewer
